{
  "header": {
    "title": "Faces By Afnitha",
    "subtitle": "Luxury Looks for Your Special Day"
  },
  "packages": [
    {
      "name": "Classic Bridal",
      "bestSeller": true,
      "offerTitle": "Limited Time Offer!",
      "actualPrice": "₹18,000",
      "offerPrice": "₹15,000",
      "features": [
        "HD Makeup",
        "Hair Styling",
        "Draping",
        "Lashes"
      ]
    },
    {
      "name": "Premium Bridal",
      "bestSeller": false,
      "offerTitle": "Summer Special",
      "actualPrice": "₹30,000",
      "offerPrice": "₹25,000",
      "features": [
        "Airbrush Makeup",
        "Advanced Hair Styling",
        "Draping",
        "Lashes",
        "Touch-up Kit"
      ]
    },
    {
      "name": "Engagement Glam",
      "bestSeller": false,
      "offerTitle": "Introductory Price",
      "actualPrice": "₹12,000",
      "offerPrice": "₹9,500",
      "features": [
        "HD Makeup",
        "Simple Hair Styling",
        "Lashes"
      ]
    },
    {
      "name": "Party Makeup",
      "bestSeller": false,
      "offerTitle": "",
      "actualPrice": "₹8,000",
      "offerPrice": "₹6,500",
      "features": [
        "HD Makeup",
        "Basic Hair Styling"
      ]
    },
    {
      "name": "Luxury Bridal",
      "bestSeller": true,
      "offerTitle": "Most Popular",
      "actualPrice": "₹40,000",
      "offerPrice": "₹32,000",
      "features": [
        "Airbrush Makeup",
        "Premium Hair Styling",
        "Draping",
        "Lashes",
        "Luxury Touch-up Kit",
        "Personal Assistant"
      ]
    }
  ],
  "portfolio": [
    "assets/p1.jpg",
    "assets/p2.jpg",
    "assets/p3.jpg"
  ],
  "contact": {
    "phone": "+91-90615 56123",
    "email": "makeupartist@email.com",
    "instagram": {
      "handle": "@faces_by_afnitha",
      "url": "https://www.instagram.com/faces_by_afnitha/"
    }
  }
} 